wiremock/VERSION
wiremock/__init__.py
wiremock/_compat.py
wiremock/base/__init__.py
wiremock/base/base_entity.py
wiremock/base/base_resource.py
wiremock/client.py
wiremock/constants.py
wiremock/exceptions/__init__.py
wiremock/exceptions/api_exception.py
wiremock/exceptions/api_unavailable_exception.py
wiremock/exceptions/client_exception.py
wiremock/exceptions/forbidden_exception.py
wiremock/exceptions/invalid_input_exception.py
wiremock/exceptions/not_found_exception.py
wiremock/exceptions/requires_login_exception.py
wiremock/exceptions/server_exception.py
wiremock/exceptions/timeout_exception.py
wiremock/exceptions/unexpected_response_exception.py
wiremock/resources/__init__.py
wiremock/resources/mappings/__init__.py
wiremock/resources/mappings/models.py
wiremock/resources/mappings/resource.py
wiremock/resources/near_misses/__init__.py
wiremock/resources/near_misses/models.py
wiremock/resources/near_misses/resource.py
wiremock/resources/requests/__init__.py
wiremock/resources/requests/models.py
wiremock/resources/requests/resource.py
wiremock/resources/scenarios/__init__.py
wiremock/resources/scenarios/resource.py
wiremock/resources/settings/__init__.py
wiremock/resources/settings/models.py
wiremock/resources/settings/resource.py
wiremock/server/__init__.py
wiremock/server/exceptions.py
wiremock/server/server.py
wiremock/server/wiremock-standalone-2.35.1.jar
wiremock/testing/__init__.py
wiremock/testing/testcontainer.py
wiremock-2.7.0.dist-info/LICENSE
wiremock-2.7.0.dist-info/METADATA
wiremock-2.7.0.dist-info/WHEEL
wiremock-2.7.0.dist-info/RECORD
