Metadata-Version: 2.1
Name: wiremock
Version: 2.7.0
Summary: Wiremock Admin API Client
License: OSI Approved :: Apache Software License
Author: Cody Lee
Author-email: cody.lee@datadoghq.com
Requires-Python: >=3.7,<4.0
Classifier: Development Status :: 5 - Production/Stable
Classifier: Environment :: Other Environment
Classifier: Environment :: Plugins
Classifier: Environment :: Web Environment
Classifier: Intended Audience :: Developers
Classifier: License :: OSI Approved :: Apache Software License
Classifier: License :: Other/Proprietary License
Classifier: Natural Language :: English
Classifier: Operating System :: OS Independent
Classifier: Programming Language :: Python :: 3
Classifier: Programming Language :: Python :: 3.7
Classifier: Programming Language :: Python :: 3.8
Classifier: Programming Language :: Python :: 3.9
Classifier: Programming Language :: Python :: 3.10
Classifier: Programming Language :: Python :: 3.11
Classifier: Programming Language :: Python :: Implementation
Classifier: Topic :: Internet :: WWW/HTTP
Classifier: Topic :: Software Development :: Libraries :: Python Modules
Classifier: Topic :: Software Development :: Quality Assurance
Classifier: Topic :: Software Development :: Testing
Classifier: Topic :: Software Development :: Testing :: Mocking
Classifier: Topic :: Software Development :: Testing :: Unit
Provides-Extra: testing
Requires-Dist: docker (>=6.1.0,<7.0.0) ; extra == "testing"
Requires-Dist: importlib-resources (>=5.12.0,<6.0.0)
Requires-Dist: requests (>=2.20.0,<3.0.0)
Requires-Dist: testcontainers (>=3.7.1,<4.0.0) ; extra == "testing"
